audio_transcript/__init__.py
audio_transcript/cli.py
audio_transcript/core.py
audio_transcript_cli-0.1.1.dist-info/licenses/LICENSE
audio_transcript_cli-0.1.1.dist-info/METADATA
audio_transcript_cli-0.1.1.dist-info/WHEEL
audio_transcript_cli-0.1.1.dist-info/entry_points.txt
audio_transcript_cli-0.1.1.dist-info/top_level.txt
audio_transcript_cli-0.1.1.dist-info/RECORD
