Metadata-Version: 2.4
Name: audio-transcript-cli
Version: 0.1.1
Summary: A simple CLI tool to transcribe large audio files using OpenAI Whisper with chunking support.
Author-email: Azmat Siddique <azmat.siddique.98@gmail.com>
Project-URL: Homepage, https://github.com/azmatsiddique/audio-transcript-cli
Project-URL: Bug Tracker, https://github.com/azmatsiddique/audio-transcript-cli/issues
Classifier: Programming Language :: Python :: 3
Classifier: License :: OSI Approved :: MIT License
Classifier: Operating System :: OS Independent
Requires-Python: >=3.8
License-File: LICENSE
Requires-Dist: transformers
Requires-Dist: torch
Requires-Dist: pydub
Requires-Dist: numpy
Requires-Dist: accelerate
Dynamic: license-file
